<annotation>
	<folder>data</folder>
	<filename>IMG_20180306_191732.jpg</filename>
	<path>/home/extra/labelImg/data/IMG_20180306_191732.jpg</path>
	<source>
		<database>Unknown</database>
	</source>
	<size>
		<width>810</width>
		<height>1080</height>
		<depth>3</depth>
	</size>
	<segmented>0</segmented>
	<object>
		<name>box</name>
		<pose>Unspecified</pose>
		<truncated>0</truncated>
		<difficult>0</difficult>
		<bndbox>
			<xmin>353</xmin>
			<ymin>365</ymin>
			<xmax>472</xmax>
			<ymax>486</ymax>
		</bndbox>
	</object>
	<object>
		<name>box</name>
		<pose>Unspecified</pose>
		<truncated>0</truncated>
		<difficult>0</difficult>
		<bndbox>
			<xmin>348</xmin>
			<ymin>481</ymin>
			<xmax>470</xmax>
			<ymax>570</ymax>
		</bndbox>
	</object>
</annotation>
